aistnet/__init__.py
aistnet/architectures/__init__.py
aistnet/architectures/unet.py
aistnet/callbacks/__init__.py
aistnet/callbacks/callbacks.py
aistnet/core/__init__.py
aistnet/core/builder.py
aistnet/core/trainer.py
aistnet/layers/__init__.py
aistnet/layers/layers.py
aistnet/losses/AistNetLoss.py
aistnet/losses/__init__.py
aistnet/losses/classification.py
aistnet/losses/regression.py
aistnet/metrics/__init__.py
aistnet/metrics/metrics.py
aistnet-1.0.0.dist-info/LICENCE
aistnet-1.0.0.dist-info/METADATA
aistnet-1.0.0.dist-info/WHEEL
aistnet-1.0.0.dist-info/top_level.txt
aistnet-1.0.0.dist-info/RECORD
