Metadata-Version: 2.1
Name: aistnet
Version: 1.0.0
Summary: AistNET is a framework for simplifying the creation and training of neural networks
Home-page: https://github.com/FHOOEAIST/aistnet
Author: AIST
Author-email: contact@aist.science
License: UNKNOWN
Project-URL: Bug Tracker, https://github.com/FHOOEAIST/aistnet/issues
Platform: UNKNOWN
Classifier: Programming Language :: Python :: 3
Classifier: License :: OSI Approved :: Mozilla Public License 2.0 (MPL 2.0)
Classifier: Operating System :: OS Independent
Requires-Python: <3.9
License-File: LICENCE
Requires-Dist: tensorflow (>=2.4.0)
Requires-Dist: numpy (==1.19.2)
Requires-Dist: pandas (==1.3.0)
Requires-Dist: dill (==0.3.4)
